azdummy/__init__.py
azdummy/__main__.py
azdummy/commands/__init__.py
azdummy/commands/config.py
azdummy/commands/gen.py
azdummy/core/__init__.py
azdummy/core/typer.py
azdummy/main.py
azdummy/provider.py
azdummy/settings.env
azdummy/settings.py
azdummy/styles.py
azdummy-1.1.2.dist-info/entry_points.txt
azdummy-1.1.2.dist-info/WHEEL
azdummy-1.1.2.dist-info/METADATA
azdummy-1.1.2.dist-info/RECORD
