Metadata-Version: 2.1
Name: azdummy
Version: 1.1.2
Summary: A Python Typer-based CLI tool to generate fake data for Azure AD.
Home-page: https://github.com/daddycocoaman/AzDummy
License: MIT
Author: Leron Gray
Requires-Python: >=3.8,<4.0
Classifier: License :: OSI Approved :: MIT License
Classifier: Programming Language :: Python :: 3
Classifier: Programming Language :: Python :: 3.8
Classifier: Programming Language :: Python :: 3.9
Requires-Dist: click-help-colors (>=0.9,<0.10)
Requires-Dist: mimesis (>=4.1.2,<5.0.0)
Requires-Dist: pydantic (>=1.7.3,<2.0.0)
Requires-Dist: python-dotenv (>=0.15.0,<0.16.0)
Requires-Dist: rich (>=9.3.0,<10.0.0)
Requires-Dist: typer[all] (>=0.3.2,<0.4.0)
